{
  "name": "Barbara Hunter",
  "age": 54,
  "address": {
    "street": "Nercom Plaza",
    "city": "Wenitwit",
    "state": "PA",
    "zip": "53719"
  },
  "contact": {
    "phone": "(244) 276-2877",
    "servicePhone": "800565113"
  },
  "birthday": "2006-08-20T10:54:10.798Z",
  "ip": "197.31.243.35",
  "foo": "bar",
  "profile": {
    "about": "Fez ug moler fun so inrom miziw tedirefo so jun ow mu il kaamaatu me. Wi ele veplu difmu vegsuci cuma wemom igo vop fan ibru bunze puh hasnus he sanveiru guhirsaz. Tugdupal rivjufci etu kuwwu ravwair uvaha zihe jo mu ej hetwecel koijoef im.",
    "bio": "Ati avotab sec hor feve zimecuco lo mumuba pimot daho he tu akaipu in zuszi vov ne gipavi. Imalofan raz ihi biga venlacavi fat entojlef jutre vognottas ebi ketabazo do. Heja ro kub na mis nejosa popofiko zi motbu keerose fa kesgaszo waltima. Wo kulet jiv ufohabbe ajnac pot inu za tituslut rijo megofwub soipu givbabasi heni jinoz cagfokli. Ri zuwofoozi du pi amaobu ec ju ip jo ra ge supmifo giuguju lizure."
  },
  "apiKey": "ecd403288dc5792eaad609832c827a0d23c8dfd3d8d2ecb27dc70605823ab779",
  "currency": {
    "code": "KHR",
    "name": "Cambodia Riel"
  }
}